push_msg/__init__.py
push_msg-0.0.1.dist-info/LICENSE
push_msg-0.0.1.dist-info/METADATA
push_msg-0.0.1.dist-info/WHEEL
push_msg-0.0.1.dist-info/top_level.txt
push_msg-0.0.1.dist-info/RECORD
