Metadata-Version: 2.1
Name: push-msg
Version: 0.0.1
Summary: Push message to wechat
Home-page: https://blog.oliverxu.cn
Author: Oliver Xu
Author-email: 273601727@qq.com
License: UNKNOWN
Platform: UNKNOWN
Classifier: Programming Language :: Python :: 3
Classifier: License :: OSI Approved :: MIT License
Classifier: Operating System :: OS Independent
